autohooks/plugins/mypy/__init__.py
autohooks/plugins/mypy/__version__.py
autohooks/plugins/mypy/mypy.py
autohooks_plugin_mypy-23.10.0.dist-info/LICENSE
autohooks_plugin_mypy-23.10.0.dist-info/METADATA
autohooks_plugin_mypy-23.10.0.dist-info/WHEEL
autohooks_plugin_mypy-23.10.0.dist-info/RECORD
