Metadata-Version: 2.1
Name: autohooks-plugin-mypy
Version: 23.10.0
Summary: An autohooks plugin for python code static typing check with mypy
Home-page: https://github.com/greenbone/autohooks-plugin-mypy
License: GPL-3.0-or-later
Keywords: git,static,typing,hooks,mypy
Author: Vincent Texier
Author-email: vit@free.fr
Requires-Python: >=3.9,<4.0
Classifier: Development Status :: 4 - Beta
Classifier: Environment :: Console
Classifier: Intended Audience :: Developers
Classifier: License :: OSI Approved :: GNU General Public License v3 or later (GPLv3+)
Classifier: Operating System :: OS Independent
Classifier: Programming Language :: Python :: 3
Classifier: Programming Language :: Python :: 3.9
Classifier: Programming Language :: Python :: 3.10
Classifier: Programming Language :: Python :: 3.11
Classifier: Programming Language :: Python :: 3.12
Classifier: Topic :: Software Development :: Libraries :: Python Modules
Requires-Dist: autohooks (>=21.7.0)
Requires-Dist: mypy (>=0.910)
Project-URL: Repository, https://github.com/greenbone/autohooks-plugin-mypy
